sensorimpactFDD/__init__.py
sensorimpactFDD/sensorimpactFDD.py
sensorimpactFDD-0.1.7.dist-info/LICENSE
sensorimpactFDD-0.1.7.dist-info/METADATA
sensorimpactFDD-0.1.7.dist-info/WHEEL
sensorimpactFDD-0.1.7.dist-info/top_level.txt
sensorimpactFDD-0.1.7.dist-info/RECORD
