Metadata-Version: 2.1
Name: sensorimpactFDD
Version: 0.1.7
Summary: Sensor impact valuation and verification analysis for fault detection and diagnostics in buildings
Home-page: https://github.com/NREL/sensor-impact-evaluation-and-verification
Author: Liang Zhang
Author-email: liang.zhang@nrel.gov
Project-URL: Bug Tracker, https://github.com/NREL/sensor-impact-evaluation-and-verification/issues
Classifier: Programming Language :: Python :: 3
Classifier: License :: OSI Approved :: MIT License
Classifier: Operating System :: OS Independent
Requires-Python: >=3.6
License-File: LICENSE
Requires-Dist: pandas
Requires-Dist: numpy
Requires-Dist: dask
Requires-Dist: gdown
Requires-Dist: scikit-learn
